pyhtml_cem/__init__.py
pyhtml_cem/__main__.py
pyhtml_cem/cem_parser.py
pyhtml_cem/py.typed
pyhtml_cem/scripts/__init__.py
pyhtml_cem/scripts/regen_webawesome.py
pyhtml_cem/webawesome/__init__.py
pyhtml_cem/webawesome/__init__.pyi
pyhtml_cem/webawesome/py.typed
pyhtml_cem/webawesome/components/__init__.py
pyhtml_cem/webawesome/components/__init__.pyi
pyhtml_cem/webawesome/components/animated_image.py
pyhtml_cem/webawesome/components/animated_image.pyi
pyhtml_cem/webawesome/components/animation.py
pyhtml_cem/webawesome/components/animation.pyi
pyhtml_cem/webawesome/components/avatar.py
pyhtml_cem/webawesome/components/avatar.pyi
pyhtml_cem/webawesome/components/badge.py
pyhtml_cem/webawesome/components/badge.pyi
pyhtml_cem/webawesome/components/breadcrumb.py
pyhtml_cem/webawesome/components/breadcrumb.pyi
pyhtml_cem/webawesome/components/breadcrumb_item.py
pyhtml_cem/webawesome/components/breadcrumb_item.pyi
pyhtml_cem/webawesome/components/button.py
pyhtml_cem/webawesome/components/button.pyi
pyhtml_cem/webawesome/components/button_group.py
pyhtml_cem/webawesome/components/button_group.pyi
pyhtml_cem/webawesome/components/callout.py
pyhtml_cem/webawesome/components/callout.pyi
pyhtml_cem/webawesome/components/card.py
pyhtml_cem/webawesome/components/card.pyi
pyhtml_cem/webawesome/components/carousel.py
pyhtml_cem/webawesome/components/carousel.pyi
pyhtml_cem/webawesome/components/carousel_item.py
pyhtml_cem/webawesome/components/carousel_item.pyi
pyhtml_cem/webawesome/components/checkbox.py
pyhtml_cem/webawesome/components/checkbox.pyi
pyhtml_cem/webawesome/components/color_picker.py
pyhtml_cem/webawesome/components/color_picker.pyi
pyhtml_cem/webawesome/components/comparison.py
pyhtml_cem/webawesome/components/comparison.pyi
pyhtml_cem/webawesome/components/copy_button.py
pyhtml_cem/webawesome/components/copy_button.pyi
pyhtml_cem/webawesome/components/details.py
pyhtml_cem/webawesome/components/details.pyi
pyhtml_cem/webawesome/components/dialog.py
pyhtml_cem-0.1.0.dist-info/licenses/LICENSE
pyhtml_cem-0.1.0.dist-info/METADATA
pyhtml_cem-0.1.0.dist-info/WHEEL
pyhtml_cem-0.1.0.dist-info/entry_points.txt
pyhtml_cem-0.1.0.dist-info/top_level.txt
pyhtml_cem-0.1.0.dist-info/RECORD
