Metadata-Version: 2.4
Name: pyhtml-cem
Version: 0.1.0
Summary: Custom Elements Manifest parser and pre-generated component libraries for PyHTML
Author: Ylan Allouche
License: MIT
Project-URL: Homepage, https://github.com/YlanAllouche/pyhtml-cem
Project-URL: Documentation, https://github.com/YlanAllouche/pyhtml-cem#readme
Project-URL: Repository, https://github.com/YlanAllouche/pyhtml-cem
Project-URL: Issues, https://github.com/YlanAllouche/pyhtml-cem/issues
Keywords: pyhtml,html,web-components,custom-elements,htmx,webawesome,shoelace
Classifier: Development Status :: 4 - Beta
Classifier: Intended Audience :: Developers
Classifier: License :: OSI Approved :: MIT License
Classifier: Programming Language :: Python :: 3
Classifier: Programming Language :: Python :: 3.10
Classifier: Programming Language :: Python :: 3.11
Classifier: Programming Language :: Python :: 3.12
Classifier: Topic :: Internet :: WWW/HTTP
Classifier: Topic :: Software Development :: Code Generators
Classifier: Topic :: Software Development :: Libraries :: Python Modules
Requires-Python: >=3.10
License-File: LICENSE
Requires-Dist: pyhtml-enhanced>=2.2.4
Dynamic: license-file
